radnlp/__init__.py
radnlp/classifier.py
radnlp/data.py
radnlp/io.py
radnlp/process.py
radnlp/radlex.py
radnlp/rules.py
radnlp/schema.py
radnlp/split.py
radnlp/utils.py
radnlp/view.py
radnlp/edit/__init__.py
radnlp/edit/notebook.py
radnlp-0.2.0.8.dist-info/DESCRIPTION.rst
radnlp-0.2.0.8.dist-info/METADATA
radnlp-0.2.0.8.dist-info/RECORD
radnlp-0.2.0.8.dist-info/WHEEL
radnlp-0.2.0.8.dist-info/metadata.json
radnlp-0.2.0.8.dist-info/top_level.txt
